cli/__init__.py
cli/main.py
crmadminbrasil_dataverse_sdk-2.0.0.dist-info/licenses/LICENSE
dataverse_sdk/__init__.py
dataverse_sdk/pagination.py
dataverse_sdk/py.typed
dataverse_sdk/auth/__init__.py
dataverse_sdk/batch/__init__.py
dataverse_sdk/client/__init__.py
dataverse_sdk/exceptions/__init__.py
dataverse_sdk/hooks/__init__.py
dataverse_sdk/models/__init__.py
dataverse_sdk/utils/__init__.py
dataverse_sdk/utils/ssl_patch.py
crmadminbrasil_dataverse_sdk-2.0.0.dist-info/METADATA
crmadminbrasil_dataverse_sdk-2.0.0.dist-info/WHEEL
crmadminbrasil_dataverse_sdk-2.0.0.dist-info/entry_points.txt
crmadminbrasil_dataverse_sdk-2.0.0.dist-info/top_level.txt
crmadminbrasil_dataverse_sdk-2.0.0.dist-info/RECORD
