Metadata-Version: 2.4
Name: crmadminbrasil-dataverse-sdk
Version: 2.0.0
Summary: Async Python SDK for Microsoft Dataverse with enterprise features
Author-email: Dataverse SDK Team <team@dataverse-sdk.com>
Maintainer-email: Dataverse SDK Team <team@dataverse-sdk.com>
License: MIT
Project-URL: Homepage, https://github.com/joseandrefilho/dataverse-sdk
Project-URL: Documentation, https://dataverse-sdk.readthedocs.io
Project-URL: Repository, https://github.com/joseandrefilho/dataverse-sdk
Project-URL: Bug Tracker, https://github.com/joseandrefilho/dataverse-sdk/issues
Project-URL: Changelog, https://github.com/joseandrefilho/dataverse-sdk/blob/main/CHANGELOG.md
Keywords: dataverse,dynamics,crm,microsoft,async,sdk
Classifier: Development Status :: 5 - Production/Stable
Classifier: Intended Audience :: Developers
Classifier: License :: OSI Approved :: MIT License
Classifier: Operating System :: OS Independent
Classifier: Programming Language :: Python :: 3
Classifier: Programming Language :: Python :: 3.8
Classifier: Programming Language :: Python :: 3.9
Classifier: Programming Language :: Python :: 3.10
Classifier: Programming Language :: Python :: 3.11
Classifier: Programming Language :: Python :: 3.12
Classifier: Topic :: Software Development :: Libraries :: Python Modules
Classifier: Topic :: Internet :: WWW/HTTP :: Dynamic Content
Classifier: Framework :: AsyncIO
Requires-Python: >=3.8
License-File: LICENSE
Requires-Dist: httpx>=0.25.0
Requires-Dist: msal>=1.24.0
Requires-Dist: pydantic>=2.0.0
Requires-Dist: typer[all]>=0.9.0
Requires-Dist: rich>=13.0.0
Requires-Dist: aiofiles>=23.0.0
Requires-Dist: tenacity>=8.2.0
Requires-Dist: structlog>=23.0.0
Requires-Dist: pandas>=2.0.0
Requires-Dist: python-dotenv>=1.0.0
Requires-Dist: xmltodict>=0.13.0
Requires-Dist: orjson>=3.9.0
Provides-Extra: dev
Requires-Dist: pytest>=7.4.0; extra == "dev"
Requires-Dist: pytest-asyncio>=0.21.0; extra == "dev"
Requires-Dist: pytest-cov>=4.1.0; extra == "dev"
Requires-Dist: pytest-mock>=3.11.0; extra == "dev"
Requires-Dist: black>=23.0.0; extra == "dev"
Requires-Dist: isort>=5.12.0; extra == "dev"
Requires-Dist: flake8>=6.0.0; extra == "dev"
Requires-Dist: mypy>=1.5.0; extra == "dev"
Requires-Dist: pre-commit>=3.4.0; extra == "dev"
Requires-Dist: bandit>=1.7.5; extra == "dev"
Requires-Dist: safety>=2.3.0; extra == "dev"
Provides-Extra: docs
Requires-Dist: mkdocs>=1.5.0; extra == "docs"
Requires-Dist: mkdocs-material>=9.2.0; extra == "docs"
Requires-Dist: mkdocstrings[python]>=0.23.0; extra == "docs"
Provides-Extra: telemetry
Requires-Dist: opentelemetry-api>=1.20.0; extra == "telemetry"
Requires-Dist: opentelemetry-sdk>=1.20.0; extra == "telemetry"
Requires-Dist: opentelemetry-instrumentation-httpx>=0.41b0; extra == "telemetry"
Dynamic: license-file
